LICENSE
MANIFEST.in
README.md
requirements-dev.txt
requirements.txt
setup.py
django_simple_contact.egg-info/PKG-INFO
django_simple_contact.egg-info/SOURCES.txt
django_simple_contact.egg-info/dependency_links.txt
django_simple_contact.egg-info/not-zip-safe
django_simple_contact.egg-info/requires.txt
django_simple_contact.egg-info/top_level.txt
simple_contact/__init__.py
simple_contact/forms.py
simple_contact/settings.py
simple_contact/urls.py
simple_contact/views.py
simple_contact/locale/pt_BR/LC_MESSAGES/django.mo
simple_contact/locale/pt_BR/LC_MESSAGES/django.po
simple_contact/templates/simple_contact/contact_email.html
simple_contact/templates/simple_contact/contact_form.html