Metadata-Version: 1.1
Name: django-simple-contact
Version: 0.3.0
Summary: Contact application for Django project
Home-page: https://github.com/kplaube/django-simple-contact
Author: Klaus Laube
Author-email: kplaube@gmail.com
License: GNU Lesser General Public License (LGPL), Version 3
Keywords: django apps contact form
Platform: UNKNOWN
Classifier: Environment :: Plugins
Classifier: Framework :: Django
Classifier: Intended Audience :: Developers
Classifier: License :: OSI Approved :: GNU Library or Lesser General Public License (LGPL)
Classifier: Operating System :: OS Independent
Classifier: Programming Language :: Python
Classifier: Topic :: Software Development :: Libraries :: Python Modules
